retrocast/__init__.py
retrocast/_version.py
retrocast/api.py
retrocast/chem.py
retrocast/exceptions.py
retrocast/paths.py
retrocast/py.typed
retrocast/typing.py
retrocast/adapters/__init__.py
retrocast/adapters/aizynth_adapter.py
retrocast/adapters/askcos_adapter.py
retrocast/adapters/base_adapter.py
retrocast/adapters/common.py
retrocast/adapters/dms_adapter.py
retrocast/adapters/dreamretro_adapter.py
retrocast/adapters/factory.py
retrocast/adapters/multistepttl_adapter.py
retrocast/adapters/paroutes_adapter.py
retrocast/adapters/retrochimera_adapter.py
retrocast/adapters/retrostar_adapter.py
retrocast/adapters/synllama_adapter.py
retrocast/adapters/synplanner_adapter.py
retrocast/adapters/syntheseus_adapter.py
retrocast/cli/__init__.py
retrocast/cli/adhoc.py
retrocast/cli/handlers.py
retrocast/cli/main.py
retrocast/curation/__init__.py
retrocast/curation/filtering.py
retrocast/curation/generators.py
retrocast/curation/sampling.py
retrocast/io/__init__.py
retrocast/io/blob.py
retrocast/io/data.py
retrocast/io/provenance.py
retrocast/metrics/__init__.py
retrocast/metrics/bootstrap.py
retrocast/metrics/diversity.py
retrocast/metrics/ranking.py
retrocast/metrics/similarity.py
retrocast/metrics/solvability.py
retrocast/models/__init__.py
retrocast/models/benchmark.py
retrocast/models/chem.py
retrocast/models/evaluation.py
retrocast/models/provenance.py
retrocast/models/stats.py
retrocast/resources/__init__.py
retrocast/resources/default_config.yaml
retrocast/utils/__init__.py
retrocast/utils/logging.py
retrocast/utils/serializers.py
retrocast/utils/timing.py
retrocast/visualization/adapters.py
retrocast/visualization/model_performance.py
retrocast/visualization/plots.py
retrocast/visualization/report.py
retrocast/visualization/routes.py
retrocast/visualization/theme.py
retrocast/workflow/__init__.py
retrocast/workflow/analyze.py
retrocast/workflow/ingest.py
retrocast/workflow/score.py
retrocast/workflow/verify.py
retrocast-0.5.3.dist-info/licenses/LICENSE
retrocast-0.5.3.dist-info/METADATA
retrocast-0.5.3.dist-info/WHEEL
retrocast-0.5.3.dist-info/entry_points.txt
retrocast-0.5.3.dist-info/top_level.txt
retrocast-0.5.3.dist-info/RECORD
