Metadata-Version: 2.4
Name: retrocast
Version: 0.5.3
Summary: a framework for ingesting, validating, canonicalizing, and adapting retrosynthesis model outputs to a unified benchmark standard.
Author-email: Anton Morgunov <anton@ischemist.com>
License: MIT
Project-URL: Homepage, https://github.com/ischemist/project-procrustes
Project-URL: Issues, https://github.com/ischemist/project-procrustes/issues
Requires-Python: >=3.11
License-File: LICENSE
Requires-Dist: packaging>=25.0
Requires-Dist: pydantic
Requires-Dist: pyyaml>=6.0.3
Requires-Dist: rdkit
Requires-Dist: rich>=14.2.0
Requires-Dist: tqdm>=4.67.1
Provides-Extra: aizyn
Requires-Dist: aizynthfinder==4.4.0; extra == "aizyn"
Requires-Dist: numpy<=2.2; extra == "aizyn"
Provides-Extra: dms
Requires-Dist: directmultistep; extra == "dms"
Provides-Extra: retro-star
Requires-Dist: retro-star>=0.1.0; extra == "retro-star"
Requires-Dist: torch; extra == "retro-star"
Provides-Extra: syntheseus
Requires-Dist: syntheseus[local-retro]>=0.5.0; extra == "syntheseus"
Requires-Dist: numpy<2; extra == "syntheseus"
Requires-Dist: pandas<2.2; extra == "syntheseus"
Requires-Dist: dgl; extra == "syntheseus"
Requires-Dist: torch<=2.1; extra == "syntheseus"
Requires-Dist: torchdata<=0.7.0; extra == "syntheseus"
Requires-Dist: faiss-cpu; extra == "syntheseus"
Requires-Dist: torch-scatter; extra == "syntheseus"
Provides-Extra: viz
Requires-Dist: ischemist>=0.2.0; extra == "viz"
Requires-Dist: kaleido>=1.1.0; extra == "viz"
Requires-Dist: plotly>=6.3.0; extra == "viz"
Dynamic: license-file
